climacell/__init__.py
climacell/api.py
climacell/config.py
climacell/exceptions.py
climacell/locator.py
climacell-0.1.0.dist-info/WHEEL
climacell-0.1.0.dist-info/METADATA
climacell-0.1.0.dist-info/RECORD
